LanguageIdentifier/LIDModel.py
LanguageIdentifier/LID_mixed_model.pkl
LanguageIdentifier/LSTMLID.py
LanguageIdentifier/LanguageIdentifier.py
LanguageIdentifier/__init__.py
LanguageIdentifier-1.1.1.dist-info/METADATA
LanguageIdentifier-1.1.1.dist-info/WHEEL
LanguageIdentifier-1.1.1.dist-info/top_level.txt
LanguageIdentifier-1.1.1.dist-info/RECORD
